superauth/__init__.py
superauth/config.py
superauth/py.typed
superauth/utils.py
superauth/apollo_io/__init__.py
superauth/apollo_io/apollo.py
superauth/celesto/__init__.py
superauth/celesto/base.py
superauth/celesto/crm/__init__.py
superauth/celesto/crm/contacts.py
superauth/google/__init__.py
superauth/google/calendar_api.py
superauth/google/creds.py
superauth/google/gmail_api.py
superauth-0.0.2.dist-info/METADATA
superauth-0.0.2.dist-info/WHEEL
superauth-0.0.2.dist-info/RECORD
