Metadata-Version: 2.4
Name: superauth
Version: 0.0.2
Summary: APIs and MCP Server for Enterprise Apps like Google, Notion, Hubspot...
Author-email: Aniket Maurya <aniket@celesto.ai>
Requires-Python: >=3.10
Requires-Dist: backoff>=2.2.1
Requires-Dist: dotenv>=0.9.9
Requires-Dist: google-api-python-client>=2.184.0
Requires-Dist: google-auth-httplib2>=0.2.0
Requires-Dist: google-auth-oauthlib>=1.2.2
Requires-Dist: google-auth>=2.41.1
Requires-Dist: httpx>=0.28.1
Requires-Dist: pydantic-settings>=2.10.1
Requires-Dist: pydantic>=2.11.9
Requires-Dist: requests>=2.32.5
